nicecall/__init__.py
nicecall/filters.py
nicecall/logger.py
nicecall/process.py
nicecall/tests/__init__.py
nicecall/tests/null_process.py
nicecall/tests/process_mock_context.py
nicecall/tests/process_stub.py
nicecall-1.0.27.dist-info/METADATA
nicecall-1.0.27.dist-info/WHEEL
nicecall-1.0.27.dist-info/top_level.txt
nicecall-1.0.27.dist-info/RECORD
