Metadata-Version: 2.4
Name: nicecall
Version: 1.0.27
Summary: A library which provides a slightly more convinient way to launch processes, compared to Python's subprocess module.
Home-page: http://go.pelicandd.com/n/python-nicecall
Author: Arseni Mourzenko
Author-email: arseni.mourzenko@pelicandd.com
License: MIT
Keywords: system subprocess process
Dynamic: author
Dynamic: author-email
Dynamic: description
Dynamic: home-page
Dynamic: keywords
Dynamic: license
Dynamic: summary
